genalg/__init__.py
genalg/main.py
genalg-1.1.0.dist-info/DESCRIPTION.rst
genalg-1.1.0.dist-info/METADATA
genalg-1.1.0.dist-info/RECORD
genalg-1.1.0.dist-info/WHEEL
genalg-1.1.0.dist-info/metadata.json
genalg-1.1.0.dist-info/top_level.txt
