Metadata-Version: 2.0
Name: genalg
Version: 1.1.0
Summary: A generalizable genetic algorithm package written in Python.
Home-page: https://github.com/joeylmaalouf/genetic-algorithm-package
Author: Joey L. Maalouf, David Roundy
Author-email: joeylmaalouf@gmail.com
License: MIT
Keywords: genetic algorithm optimization solution approximation machine learning
Platform: UNKNOWN
Classifier: Development Status :: 4 - Beta
Classifier: Intended Audience :: Developers
Classifier: Topic :: Software Development :: Libraries
Classifier: License :: OSI Approved :: MIT License
Classifier: Programming Language :: Python :: 2.7
